signaler/__init__.py
signaler/core.py
signaler-0.0.2.dist-info/LICENSE
signaler-0.0.2.dist-info/METADATA
signaler-0.0.2.dist-info/WHEEL
signaler-0.0.2.dist-info/top_level.txt
signaler-0.0.2.dist-info/RECORD
